argteller/__init__.py
argteller/argteller.py
argteller/tree/__init__.py
argteller/tree/base_node.py
argteller/tree/nodes.py
argteller/tree/tree_parser.py
argteller_orig/__init__.py
argteller_orig/argteller.py
argteller_orig/tree/__init__.py
argteller_orig/tree/base_node.py
argteller_orig/tree/nodes.py
argteller_orig/tree/tree_parser.py
argteller_orig-0.0b21.dist-info/LICENSE
argteller_orig-0.0b21.dist-info/METADATA
argteller_orig-0.0b21.dist-info/WHEEL
argteller_orig-0.0b21.dist-info/top_level.txt
argteller_orig-0.0b21.dist-info/RECORD
